{
  "project_info": {
    "project_number": "1063420202906",
    "project_id": "fir-lab-3388d",
    "storage_bucket": "fir-lab-3388d.appspot.com"
  },
  "client": [
    {
      "client_info": {
        "mobilesdk_app_id": "1:1063420202906:android:fec46b5c97fdea8a4ff423",
        "android_client_info": {
          "package_name": "com.example.firebaselab"
        }
      },
      "oauth_client": [
        {
          "client_id": "1063420202906-npkvgndhun4210uol2k20q8qqppcjm5q.apps.googleusercontent.com",
          "client_type": 3
        }
      ],
      "api_key": [
        {
          "current_key": "AIzaSyBAqHiZHb8O_OAzpTgWEKlS0hy7NmRU1uk"
        }
      ],
      "services": {
        "appinvite_service": {
          "other_platform_oauth_client": [
            {
              "client_id": "1063420202906-npkvgndhun4210uol2k20q8qqppcjm5q.apps.googleusercontent.com",
              "client_type": 3
            }
          ]
        }
      }
    }
  ],
  "configuration_version": "1"
}